README.rst
setup.cfg
setup.py
strict_hint/__init__.py
strict_hint/strict_hint.py
strict_hint.egg-info/PKG-INFO
strict_hint.egg-info/SOURCES.txt
strict_hint.egg-info/dependency_links.txt
strict_hint.egg-info/top_level.txt