Metadata-Version: 1.1
Name: strict-hint
Version: 0.3.0
Summary: Strict type runtime checks for arguments and return types.
Home-page: https://github.com/potfur/strict-hint
Author: Michal Wachowski
Author-email: wachowski.michal@gmail.com
License: UNKNOWN
Download-URL: https://github.com/potfur/strict-hint/archive/0.3.0.tar.gz
Keywords: type hint,type validation,type declaration,argument type,return type
Platform: UNKNOWN
Classifier: Intended Audience :: Developers
Classifier: Operating System :: OS Independent
Classifier: Programming Language :: Python :: 3.5
Classifier: Programming Language :: Python :: 3.6
Classifier: License :: OSI Approved :: MIT License
